gms_helpers/__init__.py
gms_helpers/__main__.py
gms_helpers/agent_setup.py
gms_helpers/asset_helper.py
gms_helpers/assets.py
gms_helpers/auto_maintenance.py
gms_helpers/base_asset.py
gms_helpers/bridge_installer.py
gms_helpers/bridge_server.py
gms_helpers/cli.py
gms_helpers/config.py
gms_helpers/diagnostics.py
gms_helpers/event_helper.py
gms_helpers/exceptions.py
gms_helpers/gms.py
gms_helpers/health.py
gms_helpers/install.py
gms_helpers/introspection.py
gms_helpers/naming_config.py
gms_helpers/reference_scanner.py
gms_helpers/results.py
gms_helpers/room_helper.py
gms_helpers/room_instance_helper.py
gms_helpers/room_layer_helper.py
gms_helpers/run_session.py
gms_helpers/runner.py
gms_helpers/runtime_manager.py
gms_helpers/test_invalid.json
gms_helpers/utils.py
gms_helpers/workflow.py
gms_helpers/commands/__init__.py
gms_helpers/commands/asset_commands.py
gms_helpers/commands/diagnostics_commands.py
gms_helpers/commands/doc_commands.py
gms_helpers/commands/event_commands.py
gms_helpers/commands/maintenance_commands.py
gms_helpers/commands/room_commands.py
gms_helpers/commands/runner_commands.py
gms_helpers/commands/skills_commands.py
gms_helpers/commands/symbol_commands.py
gms_helpers/commands/workflow_commands.py
gms_helpers/gml_docs/__init__.py
gms_helpers/gml_docs/cache.py
gms_helpers/gml_docs/fetcher.py
gms_helpers/gml_docs/search.py
gms_helpers/gml_index/__init__.py
gms_helpers/gml_index/index.py
gms_helpers/gml_index/scanner.py
gms_helpers/gml_index/symbols.py
gms_helpers/maintenance/__init__.py
gms_helpers/maintenance/clean_unused_assets.py
gms_helpers/maintenance/event_sync.py
gms_helpers/maintenance/lint.py
gms_helpers/maintenance/orphan_cleanup.py
gms_helpers/maintenance/orphans.py
gms_helpers/maintenance/path_utils.py
gms_helpers/maintenance/prune.py
gms_helpers/maintenance/static_search.py
gms_helpers/maintenance/tidy_json.py
gms_helpers/maintenance/validate_paths.py
gms_helpers/maintenance/audit/__init__.py
gms_mcp-0.1.48.dist-info/licenses/LICENSE
gms_mcp-0.1.48.dist-info/METADATA
gms_mcp-0.1.48.dist-info/WHEEL
gms_mcp-0.1.48.dist-info/entry_points.txt
gms_mcp-0.1.48.dist-info/top_level.txt
gms_mcp-0.1.48.dist-info/RECORD
