Metadata-Version: 2.4
Name: gms-mcp
Version: 0.1.48
Summary: GameMaker CLI + MCP server toolset
Author: Callum Lory, Ampersand Game Studios
License-Expression: MIT
Project-URL: Homepage, https://github.com/Ampersand-Game-Studios/gms-mcp
Project-URL: Repository, https://github.com/Ampersand-Game-Studios/gms-mcp
Project-URL: Issues, https://github.com/Ampersand-Game-Studios/gms-mcp/issues
Keywords: gamemaker,mcp,cursor,cli,tools
Classifier: Programming Language :: Python :: 3
Classifier: Programming Language :: Python :: 3 :: Only
Classifier: Programming Language :: Python :: 3.9
Classifier: Programming Language :: Python :: 3.10
Classifier: Programming Language :: Python :: 3.11
Classifier: Programming Language :: Python :: 3.12
Classifier: Programming Language :: Python :: 3.13
Requires-Python: >=3.9
License-File: LICENSE
Requires-Dist: mcp>=1.0.0
Requires-Dist: fastmcp>=0.4.1
Requires-Dist: tqdm>=4.66.0
Requires-Dist: colorama>=0.4.6
Provides-Extra: dev
Requires-Dist: pytest>=9.0.0; extra == "dev"
Requires-Dist: pytest-cov>=6.0.0; extra == "dev"
Dynamic: license-file
